clauxton/__init__.py
clauxton/__version__.py
clauxton/py.typed
clauxton/analysis/__init__.py
clauxton/analysis/decision_extractor.py
clauxton/analysis/git_analyzer.py
clauxton/analysis/pattern_extractor.py
clauxton/analysis/task_suggester.py
clauxton/cli/__init__.py
clauxton/cli/config.py
clauxton/cli/conflicts.py
clauxton/cli/main.py
clauxton/cli/mcp.py
clauxton/cli/memory.py
clauxton/cli/migrate.py
clauxton/cli/repository.py
clauxton/cli/tasks.py
clauxton/core/__init__.py
clauxton/core/confirmation_manager.py
clauxton/core/conflict_detector.py
clauxton/core/knowledge_base.py
clauxton/core/knowledge_base_compat.py
clauxton/core/memory.py
clauxton/core/memory_store.py
clauxton/core/models.py
clauxton/core/operation_history.py
clauxton/core/search.py
clauxton/core/task_manager.py
clauxton/core/task_manager_compat.py
clauxton/core/task_validator.py
clauxton/intelligence/__init__.py
clauxton/intelligence/parser.py
clauxton/intelligence/repository_map.py
clauxton/intelligence/symbol_extractor.py
clauxton/mcp/__init__.py
clauxton/mcp/server.py
clauxton/proactive/__init__.py
clauxton/proactive/behavior_tracker.py
clauxton/proactive/config.py
clauxton/proactive/context_manager.py
clauxton/proactive/event_processor.py
clauxton/proactive/file_monitor.py
clauxton/proactive/models.py
clauxton/proactive/suggestion_engine.py
clauxton/semantic/__init__.py
clauxton/semantic/embeddings.py
clauxton/semantic/indexer.py
clauxton/semantic/memory_extractor.py
clauxton/semantic/memory_linker.py
clauxton/semantic/memory_qa.py
clauxton/semantic/memory_summarizer.py
clauxton/semantic/search.py
clauxton/semantic/vector_store.py
clauxton/tui/__init__.py
clauxton/tui/app.py
clauxton/tui/config.py
clauxton/tui/keybindings.py
clauxton/tui/layouts.py
clauxton/tui/themes.py
clauxton/tui/models/__init__.py
clauxton/tui/models/suggestion.py
clauxton/tui/screens/__init__.py
clauxton/tui/screens/dashboard.py
clauxton/tui/services/__init__.py
clauxton/tui/services/autocomplete.py
clauxton-0.15.0.dist-info/METADATA
clauxton-0.15.0.dist-info/WHEEL
clauxton-0.15.0.dist-info/entry_points.txt
clauxton-0.15.0.dist-info/licenses/LICENSE
clauxton-0.15.0.dist-info/RECORD
