Metadata-Version: 2.4
Name: clauxton
Version: 0.15.0
Summary: Context that persists for Claude Code - Knowledge Base, Task Management, and Conflict Detection
Project-URL: Homepage, https://github.com/nakishiyaman/clauxton
Project-URL: Documentation, https://github.com/nakishiyaman/clauxton/wiki
Project-URL: Repository, https://github.com/nakishiyaman/clauxton
Project-URL: Issues, https://github.com/nakishiyaman/clauxton/issues
Author-email: Nakishiyama <noreply@example.com>
License: MIT
License-File: LICENSE
Keywords: ai-assistant,claude,claude-code,context,knowledge-base,mcp,plugin,task-management
Classifier: Development Status :: 4 - Beta
Classifier: Intended Audience :: Developers
Classifier: License :: OSI Approved :: MIT License
Classifier: Programming Language :: Python :: 3
Classifier: Programming Language :: Python :: 3.11
Classifier: Programming Language :: Python :: 3.12
Classifier: Topic :: Software Development :: Libraries :: Python Modules
Requires-Python: >=3.11
Requires-Dist: click>=8.1
Requires-Dist: gitpython>=3.1
Requires-Dist: mcp>=1.0
Requires-Dist: numpy>=1.24
Requires-Dist: pydantic>=2.0
Requires-Dist: pyyaml>=6.0
Requires-Dist: rich>=13.0
Requires-Dist: scikit-learn>=1.3
Requires-Dist: textual>=0.47.0
Requires-Dist: tree-sitter>=0.20
Requires-Dist: watchdog>=3.0.0
Provides-Extra: dev
Requires-Dist: bandit>=1.7; extra == 'dev'
Requires-Dist: mypy>=1.5; extra == 'dev'
Requires-Dist: pytest-asyncio>=0.21; extra == 'dev'
Requires-Dist: pytest-cov>=4.1; extra == 'dev'
Requires-Dist: pytest>=7.4; extra == 'dev'
Requires-Dist: ruff>=0.1; extra == 'dev'
Requires-Dist: types-pyyaml>=6.0; extra == 'dev'
Provides-Extra: parsers-all
Requires-Dist: py-tree-sitter-swift>=0.0.1; extra == 'parsers-all'
Requires-Dist: tree-sitter-c-sharp>=0.20; extra == 'parsers-all'
Requires-Dist: tree-sitter-cpp>=0.20; extra == 'parsers-all'
Requires-Dist: tree-sitter-go>=0.20; extra == 'parsers-all'
Requires-Dist: tree-sitter-java>=0.20; extra == 'parsers-all'
Requires-Dist: tree-sitter-javascript>=0.20; extra == 'parsers-all'
Requires-Dist: tree-sitter-kotlin>=1.0; extra == 'parsers-all'
Requires-Dist: tree-sitter-php>=0.20; extra == 'parsers-all'
Requires-Dist: tree-sitter-python>=0.20; extra == 'parsers-all'
Requires-Dist: tree-sitter-ruby>=0.20; extra == 'parsers-all'
Requires-Dist: tree-sitter-rust>=0.20; extra == 'parsers-all'
Requires-Dist: tree-sitter-typescript>=0.20; extra == 'parsers-all'
Provides-Extra: parsers-cpp
Requires-Dist: tree-sitter-cpp>=0.20; extra == 'parsers-cpp'
Provides-Extra: parsers-csharp
Requires-Dist: tree-sitter-c-sharp>=0.20; extra == 'parsers-csharp'
Provides-Extra: parsers-enterprise
Requires-Dist: tree-sitter-c-sharp>=0.20; extra == 'parsers-enterprise'
Requires-Dist: tree-sitter-java>=0.20; extra == 'parsers-enterprise'
Requires-Dist: tree-sitter-kotlin>=1.0; extra == 'parsers-enterprise'
Provides-Extra: parsers-go
Requires-Dist: tree-sitter-go>=0.20; extra == 'parsers-go'
Provides-Extra: parsers-java
Requires-Dist: tree-sitter-java>=0.20; extra == 'parsers-java'
Provides-Extra: parsers-javascript
Requires-Dist: tree-sitter-javascript>=0.20; extra == 'parsers-javascript'
Provides-Extra: parsers-kotlin
Requires-Dist: tree-sitter-kotlin>=1.0; extra == 'parsers-kotlin'
Provides-Extra: parsers-php
Requires-Dist: tree-sitter-php>=0.20; extra == 'parsers-php'
Provides-Extra: parsers-python
Requires-Dist: tree-sitter-python>=0.20; extra == 'parsers-python'
Provides-Extra: parsers-ruby
Requires-Dist: tree-sitter-ruby>=0.20; extra == 'parsers-ruby'
Provides-Extra: parsers-rust
Requires-Dist: tree-sitter-rust>=0.20; extra == 'parsers-rust'
Provides-Extra: parsers-swift
Requires-Dist: py-tree-sitter-swift>=0.0.1; extra == 'parsers-swift'
Provides-Extra: parsers-systems
Requires-Dist: tree-sitter-cpp>=0.20; extra == 'parsers-systems'
Requires-Dist: tree-sitter-go>=0.20; extra == 'parsers-systems'
Requires-Dist: tree-sitter-rust>=0.20; extra == 'parsers-systems'
Provides-Extra: parsers-typescript
Requires-Dist: tree-sitter-typescript>=0.20; extra == 'parsers-typescript'
Provides-Extra: parsers-web
Requires-Dist: tree-sitter-javascript>=0.20; extra == 'parsers-web'
Requires-Dist: tree-sitter-php>=0.20; extra == 'parsers-web'
Requires-Dist: tree-sitter-typescript>=0.20; extra == 'parsers-web'
Provides-Extra: proactive
Requires-Dist: watchdog>=3.0.0; extra == 'proactive'
Provides-Extra: semantic
Requires-Dist: faiss-cpu>=1.7.4; extra == 'semantic'
Requires-Dist: sentence-transformers>=2.3.0; extra == 'semantic'
Requires-Dist: torch>=2.1.0; extra == 'semantic'
Provides-Extra: tui
Requires-Dist: prompt-toolkit>=3.0.43; extra == 'tui'
Requires-Dist: textual>=0.47.0; extra == 'tui'
